awesome_progress_bar/__init__.py
test/__init__.py
test/test_non_thread_mode.py
test/test_thread_mode.py
awesome_progress_bar-1.7.2.dist-info/LICENSE
awesome_progress_bar-1.7.2.dist-info/METADATA
awesome_progress_bar-1.7.2.dist-info/WHEEL
awesome_progress_bar-1.7.2.dist-info/top_level.txt
awesome_progress_bar-1.7.2.dist-info/RECORD
