Metadata-Version: 2.1
Name: awesome-progress-bar
Version: 1.7.2
Summary: Progress bar for terminal
Home-page: https://github.com/yoskutik/awesome_progress_bar
Author: Yoskutik
Author-email: yoskutik@gmail.com
License: UNKNOWN
Platform: UNKNOWN
Classifier: Programming Language :: Python :: 3.4
Classifier: License :: OSI Approved :: GNU General Public License v3 or later (GPLv3+)
Classifier: Operating System :: OS Independent
Requires-Python: >=3.4
